{
    "weekday": {
      "0": [],
      "1": [],
      "2": [],
      "3": [],
      "4": [],
      "5": [],
      "6": [
        "lot 915/yellow lot"
      ],
      "7": [
        "lot 915/yellow lot"
      ],
      "8": [
        "lot 915/yellow lot"
      ],
      "9": [
        "lot 915/yellow lot"
      ],
      "10": [
        "lot 915/yellow lot"
      ],
      "11": [
        "lot 915/yellow lot"
      ],
      "12": [
        "lot 915/yellow lot"
      ],
      "13": [
        "lot 915/yellow lot"
      ],
      "14": [
        "lot 915/yellow lot"
      ],
      "15": [
        "lot 915/yellow lot"
      ],
      "16": [
        "lot 915/yellow lot"
      ],
      "17": [
        "lot 915/yellow lot",
        "lot 101",
        "lot 107",
        "lot 108",
        "lot 110",
        "lot 111",
        "lot 112",
        "lot 914/scarlet lot",
        "lot 916/green lot",
        "lot 50",
        "lot 51",
        "lot 51B",
        "lot 53A",
        "lot 54",
        "lot 58",
        "lot 58A",
        "lot 59",
        "lot 60A",
        "lot 60B",
        "lot 61",
        "lot 63",
        "lot 63B",
        "lot 63C",
        "lot 64",
        "lot 66B",
        "lot 67B",
        "lot 613",
        "lot 55",
        "lot 11 nb",
        "lot 13",
        "lot 16",
        "lot 20",
        "lot 26",
        "lot 30",
        "lot 33",
        "lot 505/cac parking deck",
        "public safety building deck",
        "lot 94",
        "lot 95",
        "lot 97",
        "lot 98A",
        "lot 98B",
        "lot 805",
        "lot 70",
        "lot 71A",
        "lot 74A",
        "lot 75",
        "lot 76",
        "lot 79A",
        "lot 79",
        "lot 81",
        "lot 82",
        "lot 83",
        "lot 84",
        "lot 86",
        "lot 88",
        "lot 96",
        "lot 96A",
        "lot 701",
        "lot 709",
        "lot A",
        "lot B",
        "lot C"
      ],
      "18": [
        "lot 915/yellow lot",
        "lot 101",
        "lot 107",
        "lot 108",
        "lot 110",
        "lot 111",
        "lot 112",
        "lot 914/scarlet lot",
        "lot 916/green lot",
        "lot 50",
        "lot 51",
        "lot 51B",
        "lot 53A",
        "lot 54",
        "lot 58",
        "lot 58A",
        "lot 59",
        "lot 60A",
        "lot 60B",
        "lot 61",
        "lot 63",
        "lot 63B",
        "lot 63C",
        "lot 64",
        "lot 66B",
        "lot 67B",
        "lot 613",
        "lot 55",
        "lot 11 nb",
        "lot 13",
        "lot 16",
        "lot 20",
        "lot 26",
        "lot 30",
        "lot 33",
        "lot 505/cac parking deck",
        "public safety building deck",
        "lot 94",
        "lot 95",
        "lot 97",
        "lot 98A",
        "lot 98B",
        "lot 805",
        "lot 70",
        "lot 71A",
        "lot 74A",
        "lot 75",
        "lot 76",
        "lot 79A",
        "lot 79",
        "lot 81",
        "lot 82",
        "lot 83",
        "lot 84",
        "lot 86",
        "lot 88",
        "lot 96",
        "lot 96A",
        "lot 701",
        "lot 709",
        "lot A",
        "lot B",
        "lot C"
      ],
      "19": [
        "lot 915/yellow lot",
        "lot 101",
        "lot 107",
        "lot 108",
        "lot 110",
        "lot 111",
        "lot 112",
        "lot 914/scarlet lot",
        "lot 916/green lot",
        "lot 50",
        "lot 51",
        "lot 51B",
        "lot 53A",
        "lot 54",
        "lot 58",
        "lot 58A",
        "lot 59",
        "lot 60A",
        "lot 60B",
        "lot 61",
        "lot 63",
        "lot 63B",
        "lot 63C",
        "lot 64",
        "lot 66B",
        "lot 67B",
        "lot 613",
        "lot 55",
        "lot 11 nb",
        "lot 13",
        "lot 16",
        "lot 20",
        "lot 26",
        "lot 30",
        "lot 33",
        "lot 505/cac parking deck",
        "public safety building deck",
        "lot 94",
        "lot 95",
        "lot 97",
        "lot 98A",
        "lot 98B",
        "lot 805",
        "lot 70",
        "lot 71A",
        "lot 74A",
        "lot 75",
        "lot 76",
        "lot 79A",
        "lot 79",
        "lot 81",
        "lot 82",
        "lot 83",
        "lot 84",
        "lot 86",
        "lot 88",
        "lot 96",
        "lot 96A",
        "lot 701",
        "lot 709",
        "lot A",
        "lot B",
        "lot C"
      ],
      "20": [
        "lot 915/yellow lot",
        "lot 101",
        "lot 107",
        "lot 108",
        "lot 110",
        "lot 111",
        "lot 112",
        "lot 914/scarlet lot",
        "lot 916/green lot",
        "lot 50",
        "lot 51",
        "lot 51B",
        "lot 53A",
        "lot 54",
        "lot 58",
        "lot 58A",
        "lot 59",
        "lot 60A",
        "lot 60B",
        "lot 61",
        "lot 63",
        "lot 63B",
        "lot 63C",
        "lot 64",
        "lot 66B",
        "lot 67B",
        "lot 613",
        "lot 55",
        "lot 11 nb",
        "lot 13",
        "lot 16",
        "lot 20",
        "lot 26",
        "lot 30",
        "lot 33",
        "lot 505/cac parking deck",
        "public safety building deck",
        "lot 94",
        "lot 95",
        "lot 97",
        "lot 98A",
        "lot 98B",
        "lot 805",
        "lot 70",
        "lot 71A",
        "lot 74A",
        "lot 75",
        "lot 76",
        "lot 79A",
        "lot 79",
        "lot 81",
        "lot 82",
        "lot 83",
        "lot 84",
        "lot 86",
        "lot 88",
        "lot 96",
        "lot 96A",
        "lot 701",
        "lot 709",
        "lot A",
        "lot B",
        "lot C"
      ],
      "21": [
        "lot 915/yellow lot",
        "lot 101",
        "lot 107",
        "lot 108",
        "lot 110",
        "lot 111",
        "lot 112",
        "lot 914/scarlet lot",
        "lot 916/green lot",
        "lot 50",
        "lot 51",
        "lot 51B",
        "lot 53A",
        "lot 54",
        "lot 58",
        "lot 58A",
        "lot 59",
        "lot 60A",
        "lot 60B",
        "lot 61",
        "lot 63",
        "lot 63B",
        "lot 63C",
        "lot 64",
        "lot 66B",
        "lot 67B",
        "lot 613",
        "lot 55",
        "lot 11 nb",
        "lot 13",
        "lot 16",
        "lot 20",
        "lot 26",
        "lot 30",
        "lot 33",
        "lot 505/cac parking deck",
        "public safety building deck",
        "lot 94",
        "lot 95",
        "lot 97",
        "lot 98A",
        "lot 98B",
        "lot 805",
        "lot 70",
        "lot 71A",
        "lot 74A",
        "lot 75",
        "lot 76",
        "lot 79A",
        "lot 79",
        "lot 81",
        "lot 82",
        "lot 83",
        "lot 84",
        "lot 86",
        "lot 88",
        "lot 96",
        "lot 96A",
        "lot 701",
        "lot 709",
        "lot A",
        "lot B",
        "lot C"
      ],
      "22": [
        "lot 915/yellow lot",
        "lot 101",
        "lot 107",
        "lot 108",
        "lot 110",
        "lot 111",
        "lot 112",
        "lot 914/scarlet lot",
        "lot 916/green lot",
        "lot 50",
        "lot 51",
        "lot 51B",
        "lot 53A",
        "lot 54",
        "lot 58",
        "lot 58A",
        "lot 59",
        "lot 60A",
        "lot 60B",
        "lot 61",
        "lot 63",
        "lot 63B",
        "lot 63C",
        "lot 64",
        "lot 66B",
        "lot 67B",
        "lot 613",
        "lot 55",
        "lot 11 nb",
        "lot 13",
        "lot 16",
        "lot 20",
        "lot 26",
        "lot 30",
        "lot 33",
        "lot 505/cac parking deck",
        "public safety building deck",
        "lot 94",
        "lot 95",
        "lot 97",
        "lot 98A",
        "lot 98B",
        "lot 805",
        "lot 70",
        "lot 71A",
        "lot 74A",
        "lot 75",
        "lot 76",
        "lot 79A",
        "lot 79",
        "lot 81",
        "lot 82",
        "lot 83",
        "lot 84",
        "lot 86",
        "lot 88",
        "lot 96",
        "lot 96A",
        "lot 701",
        "lot 709",
        "lot A",
        "lot B",
        "lot C"
      ],
      "23": [
        "lot 915/yellow lot",
        "lot 101",
        "lot 107",
        "lot 108",
        "lot 110",
        "lot 111",
        "lot 112",
        "lot 914/scarlet lot",
        "lot 916/green lot",
        "lot 50",
        "lot 51",
        "lot 51B",
        "lot 53A",
        "lot 54",
        "lot 58",
        "lot 58A",
        "lot 59",
        "lot 60A",
        "lot 60B",
        "lot 61",
        "lot 63",
        "lot 63B",
        "lot 63C",
        "lot 64",
        "lot 66B",
        "lot 67B",
        "lot 613",
        "lot 55",
        "lot 11 nb",
        "lot 13",
        "lot 16",
        "lot 20",
        "lot 26",
        "lot 30",
        "lot 33",
        "lot 505/cac parking deck",
        "public safety building deck",
        "lot 94",
        "lot 95",
        "lot 97",
        "lot 98A",
        "lot 98B",
        "lot 805",
        "lot 70",
        "lot 71A",
        "lot 74A",
        "lot 75",
        "lot 76",
        "lot 79A",
        "lot 79",
        "lot 81",
        "lot 82",
        "lot 83",
        "lot 84",
        "lot 86",
        "lot 88",
        "lot 96",
        "lot 96A",
        "lot 701",
        "lot 709",
        "lot A",
        "lot B",
        "lot C"
      ]
    },
    "weekend": {
      "0": [],
      "1": [],
      "2": [],
      "3": [],
      "4": [],
      "5": [],
      "6": [
        "lot 915/yellow lot",
        "lot 101",
        "lot 107",
        "lot 108",
        "lot 110",
        "lot 111",
        "lot 112",
        "lot 914/scarlet lot",
        "lot 916/green lot",
        "lot 50",
        "lot 51",
        "lot 51B",
        "lot 53A",
        "lot 54",
        "lot 58",
        "lot 58A",
        "lot 59",
        "lot 60A",
        "lot 60B",
        "lot 61",
        "lot 63",
        "lot 63B",
        "lot 63C",
        "lot 64",
        "lot 66B",
        "lot 67B",
        "lot 613",
        "lot 55",
        "lot 11 nb",
        "lot 13",
        "lot 16",
        "lot 20",
        "lot 26",
        "lot 30",
        "lot 33",
        "lot 505/cac parking deck",
        "public safety building deck",
        "lot 94",
        "lot 95",
        "lot 97",
        "lot 98A",
        "lot 98B",
        "lot 805",
        "lot 70",
        "lot 71A",
        "lot 74A",
        "lot 75",
        "lot 76",
        "lot 79A",
        "lot 79",
        "lot 81",
        "lot 82",
        "lot 83",
        "lot 84",
        "lot 86",
        "lot 88",
        "lot 96",
        "lot 96A",
        "lot 701",
        "lot 709",
        "lot A",
        "lot B",
        "lot C"
      ],
      "7": [
        "lot 915/yellow lot",
        "lot 101",
        "lot 107",
        "lot 108",
        "lot 110",
        "lot 111",
        "lot 112",
        "lot 914/scarlet lot",
        "lot 916/green lot",
        "lot 50",
        "lot 51",
        "lot 51B",
        "lot 53A",
        "lot 54",
        "lot 58",
        "lot 58A",
        "lot 59",
        "lot 60A",
        "lot 60B",
        "lot 61",
        "lot 63",
        "lot 63B",
        "lot 63C",
        "lot 64",
        "lot 66B",
        "lot 67B",
        "lot 613",
        "lot 55",
        "lot 11 nb",
        "lot 13",
        "lot 16",
        "lot 20",
        "lot 26",
        "lot 30",
        "lot 33",
        "lot 505/cac parking deck",
        "public safety building deck",
        "lot 94",
        "lot 95",
        "lot 97",
        "lot 98A",
        "lot 98B",
        "lot 805",
        "lot 70",
        "lot 71A",
        "lot 74A",
        "lot 75",
        "lot 76",
        "lot 79A",
        "lot 79",
        "lot 81",
        "lot 82",
        "lot 83",
        "lot 84",
        "lot 86",
        "lot 88",
        "lot 96",
        "lot 96A",
        "lot 701",
        "lot 709",
        "lot A",
        "lot B",
        "lot C"
      ],
      "8": [
        "lot 915/yellow lot",
        "lot 101",
        "lot 107",
        "lot 108",
        "lot 110",
        "lot 111",
        "lot 112",
        "lot 914/scarlet lot",
        "lot 916/green lot",
        "lot 50",
        "lot 51",
        "lot 51B",
        "lot 53A",
        "lot 54",
        "lot 58",
        "lot 58A",
        "lot 59",
        "lot 60A",
        "lot 60B",
        "lot 61",
        "lot 63",
        "lot 63B",
        "lot 63C",
        "lot 64",
        "lot 66B",
        "lot 67B",
        "lot 613",
        "lot 55",
        "lot 11 nb",
        "lot 13",
        "lot 16",
        "lot 20",
        "lot 26",
        "lot 30",
        "lot 33",
        "lot 505/cac parking deck",
        "public safety building deck",
        "lot 94",
        "lot 95",
        "lot 97",
        "lot 98A",
        "lot 98B",
        "lot 805",
        "lot 70",
        "lot 71A",
        "lot 74A",
        "lot 75",
        "lot 76",
        "lot 79A",
        "lot 79",
        "lot 81",
        "lot 82",
        "lot 83",
        "lot 84",
        "lot 86",
        "lot 88",
        "lot 96",
        "lot 96A",
        "lot 701",
        "lot 709",
        "lot A",
        "lot B",
        "lot C"
      ],
      "9": [
        "lot 915/yellow lot",
        "lot 101",
        "lot 107",
        "lot 108",
        "lot 110",
        "lot 111",
        "lot 112",
        "lot 914/scarlet lot",
        "lot 916/green lot",
        "lot 50",
        "lot 51",
        "lot 51B",
        "lot 53A",
        "lot 54",
        "lot 58",
        "lot 58A",
        "lot 59",
        "lot 60A",
        "lot 60B",
        "lot 61",
        "lot 63",
        "lot 63B",
        "lot 63C",
        "lot 64",
        "lot 66B",
        "lot 67B",
        "lot 613",
        "lot 55",
        "lot 11 nb",
        "lot 13",
        "lot 16",
        "lot 20",
        "lot 26",
        "lot 30",
        "lot 33",
        "lot 505/cac parking deck",
        "public safety building deck",
        "lot 94",
        "lot 95",
        "lot 97",
        "lot 98A",
        "lot 98B",
        "lot 805",
        "lot 70",
        "lot 71A",
        "lot 74A",
        "lot 75",
        "lot 76",
        "lot 79A",
        "lot 79",
        "lot 81",
        "lot 82",
        "lot 83",
        "lot 84",
        "lot 86",
        "lot 88",
        "lot 96",
        "lot 96A",
        "lot 701",
        "lot 709",
        "lot A",
        "lot B",
        "lot C"
      ],
      "10": [
        "lot 915/yellow lot",
        "lot 101",
        "lot 107",
        "lot 108",
        "lot 110",
        "lot 111",
        "lot 112",
        "lot 914/scarlet lot",
        "lot 916/green lot",
        "lot 50",
        "lot 51",
        "lot 51B",
        "lot 53A",
        "lot 54",
        "lot 58",
        "lot 58A",
        "lot 59",
        "lot 60A",
        "lot 60B",
        "lot 61",
        "lot 63",
        "lot 63B",
        "lot 63C",
        "lot 64",
        "lot 66B",
        "lot 67B",
        "lot 613",
        "lot 55",
        "lot 11 nb",
        "lot 13",
        "lot 16",
        "lot 20",
        "lot 26",
        "lot 30",
        "lot 33",
        "lot 505/cac parking deck",
        "public safety building deck",
        "lot 94",
        "lot 95",
        "lot 97",
        "lot 98A",
        "lot 98B",
        "lot 805",
        "lot 70",
        "lot 71A",
        "lot 74A",
        "lot 75",
        "lot 76",
        "lot 79A",
        "lot 79",
        "lot 81",
        "lot 82",
        "lot 83",
        "lot 84",
        "lot 86",
        "lot 88",
        "lot 96",
        "lot 96A",
        "lot 701",
        "lot 709",
        "lot A",
        "lot B",
        "lot C"
      ],
      "11": [
        "lot 915/yellow lot",
        "lot 101",
        "lot 107",
        "lot 108",
        "lot 110",
        "lot 111",
        "lot 112",
        "lot 914/scarlet lot",
        "lot 916/green lot",
        "lot 50",
        "lot 51",
        "lot 51B",
        "lot 53A",
        "lot 54",
        "lot 58",
        "lot 58A",
        "lot 59",
        "lot 60A",
        "lot 60B",
        "lot 61",
        "lot 63",
        "lot 63B",
        "lot 63C",
        "lot 64",
        "lot 66B",
        "lot 67B",
        "lot 613",
        "lot 55",
        "lot 11 nb",
        "lot 13",
        "lot 16",
        "lot 20",
        "lot 26",
        "lot 30",
        "lot 33",
        "lot 505/cac parking deck",
        "public safety building deck",
        "lot 94",
        "lot 95",
        "lot 97",
        "lot 98A",
        "lot 98B",
        "lot 805",
        "lot 70",
        "lot 71A",
        "lot 74A",
        "lot 75",
        "lot 76",
        "lot 79A",
        "lot 79",
        "lot 81",
        "lot 82",
        "lot 83",
        "lot 84",
        "lot 86",
        "lot 88",
        "lot 96",
        "lot 96A",
        "lot 701",
        "lot 709",
        "lot A",
        "lot B",
        "lot C"
      ],
      "12": [
        "lot 915/yellow lot",
        "lot 101",
        "lot 107",
        "lot 108",
        "lot 110",
        "lot 111",
        "lot 112",
        "lot 914/scarlet lot",
        "lot 916/green lot",
        "lot 50",
        "lot 51",
        "lot 51B",
        "lot 53A",
        "lot 54",
        "lot 58",
        "lot 58A",
        "lot 59",
        "lot 60A",
        "lot 60B",
        "lot 61",
        "lot 63",
        "lot 63B",
        "lot 63C",
        "lot 64",
        "lot 66B",
        "lot 67B",
        "lot 613",
        "lot 55",
        "lot 11 nb",
        "lot 13",
        "lot 16",
        "lot 20",
        "lot 26",
        "lot 30",
        "lot 33",
        "lot 505/cac parking deck",
        "public safety building deck",
        "lot 94",
        "lot 95",
        "lot 97",
        "lot 98A",
        "lot 98B",
        "lot 805",
        "lot 70",
        "lot 71A",
        "lot 74A",
        "lot 75",
        "lot 76",
        "lot 79A",
        "lot 79",
        "lot 81",
        "lot 82",
        "lot 83",
        "lot 84",
        "lot 86",
        "lot 88",
        "lot 96",
        "lot 96A",
        "lot 701",
        "lot 709",
        "lot A",
        "lot B",
        "lot C"
      ],
      "13": [
        "lot 915/yellow lot",
        "lot 101",
        "lot 107",
        "lot 108",
        "lot 110",
        "lot 111",
        "lot 112",
        "lot 914/scarlet lot",
        "lot 916/green lot",
        "lot 50",
        "lot 51",
        "lot 51B",
        "lot 53A",
        "lot 54",
        "lot 58",
        "lot 58A",
        "lot 59",
        "lot 60A",
        "lot 60B",
        "lot 61",
        "lot 63",
        "lot 63B",
        "lot 63C",
        "lot 64",
        "lot 66B",
        "lot 67B",
        "lot 613",
        "lot 55",
        "lot 11 nb",
        "lot 13",
        "lot 16",
        "lot 20",
        "lot 26",
        "lot 30",
        "lot 33",
        "lot 505/cac parking deck",
        "public safety building deck",
        "lot 94",
        "lot 95",
        "lot 97",
        "lot 98A",
        "lot 98B",
        "lot 805",
        "lot 70",
        "lot 71A",
        "lot 74A",
        "lot 75",
        "lot 76",
        "lot 79A",
        "lot 79",
        "lot 81",
        "lot 82",
        "lot 83",
        "lot 84",
        "lot 86",
        "lot 88",
        "lot 96",
        "lot 96A",
        "lot 701",
        "lot 709",
        "lot A",
        "lot B",
        "lot C"
      ],
      "14": [
        "lot 915/yellow lot",
        "lot 101",
        "lot 107",
        "lot 108",
        "lot 110",
        "lot 111",
        "lot 112",
        "lot 914/scarlet lot",
        "lot 916/green lot",
        "lot 50",
        "lot 51",
        "lot 51B",
        "lot 53A",
        "lot 54",
        "lot 58",
        "lot 58A",
        "lot 59",
        "lot 60A",
        "lot 60B",
        "lot 61",
        "lot 63",
        "lot 63B",
        "lot 63C",
        "lot 64",
        "lot 66B",
        "lot 67B",
        "lot 613",
        "lot 55",
        "lot 11 nb",
        "lot 13",
        "lot 16",
        "lot 20",
        "lot 26",
        "lot 30",
        "lot 33",
        "lot 505/cac parking deck",
        "public safety building deck",
        "lot 94",
        "lot 95",
        "lot 97",
        "lot 98A",
        "lot 98B",
        "lot 805",
        "lot 70",
        "lot 71A",
        "lot 74A",
        "lot 75",
        "lot 76",
        "lot 79A",
        "lot 79",
        "lot 81",
        "lot 82",
        "lot 83",
        "lot 84",
        "lot 86",
        "lot 88",
        "lot 96",
        "lot 96A",
        "lot 701",
        "lot 709",
        "lot A",
        "lot B",
        "lot C"
      ],
      "15": [
        "lot 915/yellow lot",
        "lot 101",
        "lot 107",
        "lot 108",
        "lot 110",
        "lot 111",
        "lot 112",
        "lot 914/scarlet lot",
        "lot 916/green lot",
        "lot 50",
        "lot 51",
        "lot 51B",
        "lot 53A",
        "lot 54",
        "lot 58",
        "lot 58A",
        "lot 59",
        "lot 60A",
        "lot 60B",
        "lot 61",
        "lot 63",
        "lot 63B",
        "lot 63C",
        "lot 64",
        "lot 66B",
        "lot 67B",
        "lot 613",
        "lot 55",
        "lot 11 nb",
        "lot 13",
        "lot 16",
        "lot 20",
        "lot 26",
        "lot 30",
        "lot 33",
        "lot 505/cac parking deck",
        "public safety building deck",
        "lot 94",
        "lot 95",
        "lot 97",
        "lot 98A",
        "lot 98B",
        "lot 805",
        "lot 70",
        "lot 71A",
        "lot 74A",
        "lot 75",
        "lot 76",
        "lot 79A",
        "lot 79",
        "lot 81",
        "lot 82",
        "lot 83",
        "lot 84",
        "lot 86",
        "lot 88",
        "lot 96",
        "lot 96A",
        "lot 701",
        "lot 709",
        "lot A",
        "lot B",
        "lot C"
      ],
      "16": [
        "lot 915/yellow lot",
        "lot 101",
        "lot 107",
        "lot 108",
        "lot 110",
        "lot 111",
        "lot 112",
        "lot 914/scarlet lot",
        "lot 916/green lot",
        "lot 50",
        "lot 51",
        "lot 51B",
        "lot 53A",
        "lot 54",
        "lot 58",
        "lot 58A",
        "lot 59",
        "lot 60A",
        "lot 60B",
        "lot 61",
        "lot 63",
        "lot 63B",
        "lot 63C",
        "lot 64",
        "lot 66B",
        "lot 67B",
        "lot 613",
        "lot 55",
        "lot 11 nb",
        "lot 13",
        "lot 16",
        "lot 20",
        "lot 26",
        "lot 30",
        "lot 33",
        "lot 505/cac parking deck",
        "public safety building deck",
        "lot 94",
        "lot 95",
        "lot 97",
        "lot 98A",
        "lot 98B",
        "lot 805",
        "lot 70",
        "lot 71A",
        "lot 74A",
        "lot 75",
        "lot 76",
        "lot 79A",
        "lot 79",
        "lot 81",
        "lot 82",
        "lot 83",
        "lot 84",
        "lot 86",
        "lot 88",
        "lot 96",
        "lot 96A",
        "lot 701",
        "lot 709",
        "lot A",
        "lot B",
        "lot C"
      ],
      "17": [
        "lot 915/yellow lot",
        "lot 101",
        "lot 107",
        "lot 108",
        "lot 110",
        "lot 111",
        "lot 112",
        "lot 914/scarlet lot",
        "lot 916/green lot",
        "lot 50",
        "lot 51",
        "lot 51B",
        "lot 53A",
        "lot 54",
        "lot 58",
        "lot 58A",
        "lot 59",
        "lot 60A",
        "lot 60B",
        "lot 61",
        "lot 63",
        "lot 63B",
        "lot 63C",
        "lot 64",
        "lot 66B",
        "lot 67B",
        "lot 613",
        "lot 55",
        "lot 11 nb",
        "lot 13",
        "lot 16",
        "lot 20",
        "lot 26",
        "lot 30",
        "lot 33",
        "lot 505/cac parking deck",
        "public safety building deck",
        "lot 94",
        "lot 95",
        "lot 97",
        "lot 98A",
        "lot 98B",
        "lot 805",
        "lot 70",
        "lot 71A",
        "lot 74A",
        "lot 75",
        "lot 76",
        "lot 79A",
        "lot 79",
        "lot 81",
        "lot 82",
        "lot 83",
        "lot 84",
        "lot 86",
        "lot 88",
        "lot 96",
        "lot 96A",
        "lot 701",
        "lot 709",
        "lot A",
        "lot B",
        "lot C"
      ],
      "18": [
        "lot 915/yellow lot",
        "lot 101",
        "lot 107",
        "lot 108",
        "lot 110",
        "lot 111",
        "lot 112",
        "lot 914/scarlet lot",
        "lot 916/green lot",
        "lot 50",
        "lot 51",
        "lot 51B",
        "lot 53A",
        "lot 54",
        "lot 58",
        "lot 58A",
        "lot 59",
        "lot 60A",
        "lot 60B",
        "lot 61",
        "lot 63",
        "lot 63B",
        "lot 63C",
        "lot 64",
        "lot 66B",
        "lot 67B",
        "lot 613",
        "lot 55",
        "lot 11 nb",
        "lot 13",
        "lot 16",
        "lot 20",
        "lot 26",
        "lot 30",
        "lot 33",
        "lot 505/cac parking deck",
        "public safety building deck",
        "lot 94",
        "lot 95",
        "lot 97",
        "lot 98A",
        "lot 98B",
        "lot 805",
        "lot 70",
        "lot 71A",
        "lot 74A",
        "lot 75",
        "lot 76",
        "lot 79A",
        "lot 79",
        "lot 81",
        "lot 82",
        "lot 83",
        "lot 84",
        "lot 86",
        "lot 88",
        "lot 96",
        "lot 96A",
        "lot 701",
        "lot 709",
        "lot A",
        "lot B",
        "lot C"
      ],
      "19": [
        "lot 915/yellow lot",
        "lot 101",
        "lot 107",
        "lot 108",
        "lot 110",
        "lot 111",
        "lot 112",
        "lot 914/scarlet lot",
        "lot 916/green lot",
        "lot 50",
        "lot 51",
        "lot 51B",
        "lot 53A",
        "lot 54",
        "lot 58",
        "lot 58A",
        "lot 59",
        "lot 60A",
        "lot 60B",
        "lot 61",
        "lot 63",
        "lot 63B",
        "lot 63C",
        "lot 64",
        "lot 66B",
        "lot 67B",
        "lot 613",
        "lot 55",
        "lot 11 nb",
        "lot 13",
        "lot 16",
        "lot 20",
        "lot 26",
        "lot 30",
        "lot 33",
        "lot 505/cac parking deck",
        "public safety building deck",
        "lot 94",
        "lot 95",
        "lot 97",
        "lot 98A",
        "lot 98B",
        "lot 805",
        "lot 70",
        "lot 71A",
        "lot 74A",
        "lot 75",
        "lot 76",
        "lot 79A",
        "lot 79",
        "lot 81",
        "lot 82",
        "lot 83",
        "lot 84",
        "lot 86",
        "lot 88",
        "lot 96",
        "lot 96A",
        "lot 701",
        "lot 709",
        "lot A",
        "lot B",
        "lot C"
      ],
      "20": [
        "lot 915/yellow lot",
        "lot 101",
        "lot 107",
        "lot 108",
        "lot 110",
        "lot 111",
        "lot 112",
        "lot 914/scarlet lot",
        "lot 916/green lot",
        "lot 50",
        "lot 51",
        "lot 51B",
        "lot 53A",
        "lot 54",
        "lot 58",
        "lot 58A",
        "lot 59",
        "lot 60A",
        "lot 60B",
        "lot 61",
        "lot 63",
        "lot 63B",
        "lot 63C",
        "lot 64",
        "lot 66B",
        "lot 67B",
        "lot 613",
        "lot 55",
        "lot 11 nb",
        "lot 13",
        "lot 16",
        "lot 20",
        "lot 26",
        "lot 30",
        "lot 33",
        "lot 505/cac parking deck",
        "public safety building deck",
        "lot 94",
        "lot 95",
        "lot 97",
        "lot 98A",
        "lot 98B",
        "lot 805",
        "lot 70",
        "lot 71A",
        "lot 74A",
        "lot 75",
        "lot 76",
        "lot 79A",
        "lot 79",
        "lot 81",
        "lot 82",
        "lot 83",
        "lot 84",
        "lot 86",
        "lot 88",
        "lot 96",
        "lot 96A",
        "lot 701",
        "lot 709",
        "lot A",
        "lot B",
        "lot C"
      ],
      "21": [
        "lot 915/yellow lot",
        "lot 101",
        "lot 107",
        "lot 108",
        "lot 110",
        "lot 111",
        "lot 112",
        "lot 914/scarlet lot",
        "lot 916/green lot",
        "lot 50",
        "lot 51",
        "lot 51B",
        "lot 53A",
        "lot 54",
        "lot 58",
        "lot 58A",
        "lot 59",
        "lot 60A",
        "lot 60B",
        "lot 61",
        "lot 63",
        "lot 63B",
        "lot 63C",
        "lot 64",
        "lot 66B",
        "lot 67B",
        "lot 613",
        "lot 55",
        "lot 11 nb",
        "lot 13",
        "lot 16",
        "lot 20",
        "lot 26",
        "lot 30",
        "lot 33",
        "lot 505/cac parking deck",
        "public safety building deck",
        "lot 94",
        "lot 95",
        "lot 97",
        "lot 98A",
        "lot 98B",
        "lot 805",
        "lot 70",
        "lot 71A",
        "lot 74A",
        "lot 75",
        "lot 76",
        "lot 79A",
        "lot 79",
        "lot 81",
        "lot 82",
        "lot 83",
        "lot 84",
        "lot 86",
        "lot 88",
        "lot 96",
        "lot 96A",
        "lot 701",
        "lot 709",
        "lot A",
        "lot B",
        "lot C"
      ],
      "22": [
        "lot 915/yellow lot",
        "lot 101",
        "lot 107",
        "lot 108",
        "lot 110",
        "lot 111",
        "lot 112",
        "lot 914/scarlet lot",
        "lot 916/green lot",
        "lot 50",
        "lot 51",
        "lot 51B",
        "lot 53A",
        "lot 54",
        "lot 58",
        "lot 58A",
        "lot 59",
        "lot 60A",
        "lot 60B",
        "lot 61",
        "lot 63",
        "lot 63B",
        "lot 63C",
        "lot 64",
        "lot 66B",
        "lot 67B",
        "lot 613",
        "lot 55",
        "lot 11 nb",
        "lot 13",
        "lot 16",
        "lot 20",
        "lot 26",
        "lot 30",
        "lot 33",
        "lot 505/cac parking deck",
        "public safety building deck",
        "lot 94",
        "lot 95",
        "lot 97",
        "lot 98A",
        "lot 98B",
        "lot 805",
        "lot 70",
        "lot 71A",
        "lot 74A",
        "lot 75",
        "lot 76",
        "lot 79A",
        "lot 79",
        "lot 81",
        "lot 82",
        "lot 83",
        "lot 84",
        "lot 86",
        "lot 88",
        "lot 96",
        "lot 96A",
        "lot 701",
        "lot 709",
        "lot A",
        "lot B",
        "lot C"
      ],
      "23": [
        "lot 915/yellow lot",
        "lot 101",
        "lot 107",
        "lot 108",
        "lot 110",
        "lot 111",
        "lot 112",
        "lot 914/scarlet lot",
        "lot 916/green lot",
        "lot 50",
        "lot 51",
        "lot 51B",
        "lot 53A",
        "lot 54",
        "lot 58",
        "lot 58A",
        "lot 59",
        "lot 60A",
        "lot 60B",
        "lot 61",
        "lot 63",
        "lot 63B",
        "lot 63C",
        "lot 64",
        "lot 66B",
        "lot 67B",
        "lot 613",
        "lot 55",
        "lot 11 nb",
        "lot 13",
        "lot 16",
        "lot 20",
        "lot 26",
        "lot 30",
        "lot 33",
        "lot 505/cac parking deck",
        "public safety building deck",
        "lot 94",
        "lot 95",
        "lot 97",
        "lot 98A",
        "lot 98B",
        "lot 805",
        "lot 70",
        "lot 71A",
        "lot 74A",
        "lot 75",
        "lot 76",
        "lot 79A",
        "lot 79",
        "lot 81",
        "lot 82",
        "lot 83",
        "lot 84",
        "lot 86",
        "lot 88",
        "lot 96",
        "lot 96A",
        "lot 701",
        "lot 709",
        "lot A",
        "lot B",
        "lot C"
      ]
    }
  }